datatableview/__init__.py
datatableview/cache.py
datatableview/columns.py
datatableview/datatables.py
datatableview/exceptions.py
datatableview/forms.py
datatableview/helpers.py
datatableview/models.py
datatableview/utils.py
datatableview/static/js/datatableview.js
datatableview/static/js/datatableview.min.js
datatableview/templates/datatableview/bootstrap_structure.html
datatableview/templates/datatableview/default_structure.html
datatableview/templates/datatableview/legacy_structure.html
datatableview/tests/__init__.py
datatableview/tests/test_columns.py
datatableview/tests/test_datatables.py
datatableview/tests/test_helpers.py
datatableview/tests/test_utils.py
datatableview/tests/test_views.py
datatableview/tests/testcase.py
datatableview/views/__init__.py
datatableview/views/base.py
datatableview/views/legacy.py
datatableview/views/xeditable.py
django_datatable_view-2.1.6.dist-info/LICENSE.txt
django_datatable_view-2.1.6.dist-info/METADATA
django_datatable_view-2.1.6.dist-info/WHEEL
django_datatable_view-2.1.6.dist-info/top_level.txt
django_datatable_view-2.1.6.dist-info/RECORD
