Metadata-Version: 2.1
Name: django-datatable-view
Version: 2.1.6
Summary: This package is used in conjunction with the jQuery plugin (http://http://datatables.net/), and supports state-saving detection with (http://datatables.net/plug-ins/api).  The package consists of a class-based view, and a small collection of utilities for rendering table data from models.
Home-page: https://github.com/pivotal-energy-solutions/django-datatable-view
Author: Autumn Valenta
Author-email: avalenta@pivotalenergysolutions.com
License: Apache License (2.0)
Platform: UNKNOWN
Classifier: Development Status :: 5 - Production/Stable
Classifier: Environment :: Web Environment
Classifier: Framework :: Django
Classifier: Framework :: Django :: 2.1
Classifier: Framework :: Django :: 2.2
Classifier: Framework :: Django :: 3.0
Classifier: Framework :: Django :: 3.1
Classifier: Framework :: Django :: 3.2
Classifier: Intended Audience :: Developers
Classifier: License :: OSI Approved :: Apache Software License
Classifier: Operating System :: OS Independent
Classifier: Programming Language :: Python
Classifier: Programming Language :: Python :: 3
Classifier: Programming Language :: Python :: 3.8
Classifier: Programming Language :: Python :: 3.9
Classifier: Programming Language :: Python :: 3.10
Classifier: Topic :: Software Development
Requires-Python: >=3.8.*
